uptwine.py
uptwine-0.0.9.dist-info/LICENSE
uptwine-0.0.9.dist-info/METADATA
uptwine-0.0.9.dist-info/WHEEL
uptwine-0.0.9.dist-info/top_level.txt
uptwine-0.0.9.dist-info/RECORD
